notes_sdk/__init__.py
notes_sdk/client.py
notes_sdk/exceptions.py
notes_sdk/models.py
notes_service_sdk-0.1.0.dist-info/METADATA
notes_service_sdk-0.1.0.dist-info/WHEEL
notes_service_sdk-0.1.0.dist-info/top_level.txt
notes_service_sdk-0.1.0.dist-info/RECORD
