Metadata-Version: 2.4
Name: notes-service-sdk
Version: 0.1.0
Summary: A simple SDK for the Notes Service API
Author-email: Panindra Kumar <panindrakumar84@gmail.com>
Project-URL: Homepage, https://github.com/panindrakumar84/notes-service
Classifier: Programming Language :: Python :: 3
Classifier: License :: OSI Approved :: MIT License
Classifier: Operating System :: OS Independent
Requires-Python: >=3.8
Requires-Dist: httpx[http2]>=0.25.0
Requires-Dist: pydantic>=2.0
